{
  "version": 1,
  "last_updated": "2026-01-19",
  "distros": [
    {
      "id": "ubuntu-24.04-lts-desktop",
      "name": "Ubuntu 24.04 LTS Desktop",
      "version": "24.04.3 LTS",
      "category": "ubuntu",
      "download_url": "https://releases.ubuntu.com/24.04/ubuntu-24.04.3-desktop-amd64.iso",
      "sha256": "PLACEHOLDER_HASH_UPDATE_WITH_REAL_HASH",
      "size_bytes": 6100000000,
      "size_human": "5.7 GB",
      "description": "Long-term support release with GNOME desktop",
      "verified": true
    },
    {
      "id": "ubuntu-24.10-desktop",
      "name": "Ubuntu 24.10 Desktop",
      "version": "24.10",
      "category": "ubuntu",
      "download_url": "https://releases.ubuntu.com/24.10/ubuntu-24.10-desktop-amd64.iso",
      "sha256": "PLACEHOLDER_HASH_UPDATE_WITH_REAL_HASH",
      "size_bytes": 6200000000,
      "size_human": "5.8 GB",
      "description": "Latest stable release with GNOME desktop",
      "verified": true
    },
    {
      "id": "kubuntu-24.04-lts",
      "name": "Kubuntu 24.04.3 LTS",
      "version": "24.04.3 LTS",
      "category": "ubuntu",
      "download_url": "https://cdimage.ubuntu.com/kubuntu/releases/24.04.3/release/kubuntu-24.04.3-desktop-amd64.iso",
      "sha256": "PLACEHOLDER_HASH_UPDATE_WITH_REAL_HASH",
      "size_bytes": 4348000000,
      "size_human": "4.1 GB",
      "description": "Ubuntu + KDE Plasma • x86_64 • beautiful",
      "verified": true
    },
    {
      "id": "pop-os-22.04",
      "name": "Pop!_OS 22.04 LTS",
      "version": "22.04 LTS",
      "category": "ubuntu",
      "download_url": "https://iso.pop-os.org/22.04/amd64/intel/50/pop-os_22.04_amd64_intel_50.iso",
      "sha256": "PLACEHOLDER_HASH_UPDATE_WITH_REAL_HASH",
      "size_bytes": 3000000000,
      "size_human": "2.8 GB",
      "description": "System76's gaming and development focused distro",
      "verified": true
    },
    {
      "id": "fedora-41-workstation",
      "name": "Fedora Workstation 42",
      "version": "42",
      "category": "fedora",
      "download_url": "https://download.fedoraproject.org/pub/fedora/linux/releases/42/Workstation/x86_64/iso/Fedora-Workstation-Live-x86_64-42-1.1.iso",
      "sha256": "PLACEHOLDER_HASH_UPDATE_WITH_REAL_HASH",
      "size_bytes": 2100000000,
      "size_human": "2.0 GB",
      "description": "Cutting-edge with latest GNOME",
      "verified": true
    },
    {
      "id": "fedora-41-kde",
      "name": "Fedora KDE Plasma 41",
      "version": "41",
      "category": "fedora",
      "download_url": "https://download.fedoraproject.org/pub/fedora/linux/releases/41/Spins/x86_64/iso/Fedora-KDE-Live-x86_64-41-1.4.iso",
      "sha256": "PLACEHOLDER_HASH_UPDATE_WITH_REAL_HASH",
      "size_bytes": 2200000000,
      "size_human": "2.1 GB",
      "description": "Fedora with KDE Plasma desktop",
      "verified": true
    },
    {
      "id": "mint-22-cinnamon",
      "name": "Linux Mint 22 Cinnamon",
      "version": "22",
      "category": "mint",
      "download_url": "https://mirrors.kernel.org/linuxmint/stable/22/linuxmint-22-cinnamon-64bit.iso",
      "sha256": "PLACEHOLDER_HASH_UPDATE_WITH_REAL_HASH",
      "size_bytes": 2900000000,
      "size_human": "2.7 GB",
      "description": "User-friendly desktop based on Ubuntu LTS",
      "verified": true
    },
    {
      "id": "mint-22-xfce",
      "name": "Linux Mint 22 Xfce",
      "version": "22",
      "category": "mint",
      "download_url": "https://mirrors.kernel.org/linuxmint/stable/22/linuxmint-22-xfce-64bit.iso",
      "sha256": "PLACEHOLDER_HASH_UPDATE_WITH_REAL_HASH",
      "size_bytes": 2700000000,
      "size_human": "2.5 GB",
      "description": "Lightweight Xfce edition",
      "verified": true
    },
    {
      "id": "debian-13-live",
      "name": "Debian 13 Live",
      "version": "13.3.0",
      "category": "debian",
      "download_url": "https://cdimage.debian.org/debian-cd/current-live/amd64/iso-hybrid/debian-live-13.3.0-amd64-standard.iso",
      "sha256": "PLACEHOLDER_HASH_UPDATE_WITH_REAL_HASH",
      "size_bytes": 500000000,
      "size_human": "476 MB",
      "description": "Stable and reliable Linux distribution",
      "verified": true
    },
    {
      "id": "debian-13-gnome",
      "name": "Debian 13 GNOME",
      "version": "13.3.0",
      "category": "debian",
      "download_url": "https://cdimage.debian.org/debian-cd/current-live/amd64/iso-hybrid/debian-live-13.3.0-amd64-gnome.iso",
      "sha256": "PLACEHOLDER_HASH_UPDATE_WITH_REAL_HASH",
      "size_bytes": 3200000000,
      "size_human": "3.0 GB",
      "description": "Debian with GNOME desktop",
      "verified": true
    },
    {
      "id": "arch-2026.01",
      "name": "Arch Linux",
      "version": "2026.01.01",
      "category": "arch",
      "download_url": "https://mirror.rackspace.com/archlinux/iso/latest/archlinux-2026.01.01-x86_64.iso",
      "sha256": "PLACEHOLDER_HASH_UPDATE_WITH_REAL_HASH",
      "size_bytes": 900000000,
      "size_human": "858 MB",
      "description": "Rolling release for advanced users",
      "verified": true
    },
    {
      "id": "manjaro-gnome-23.1",
      "name": "Manjaro GNOME",
      "version": "23.1",
      "category": "arch",
      "download_url": "https://download.manjaro.org/gnome/23.1.4/manjaro-gnome-23.1.4-240406-linux66.iso",
      "sha256": "PLACEHOLDER_HASH_UPDATE_WITH_REAL_HASH",
      "size_bytes": 3600000000,
      "size_human": "3.4 GB",
      "description": "User-friendly Arch-based distro",
      "verified": true
    },
    {
      "id": "opensuse-tumbleweed",
      "name": "openSUSE Tumbleweed",
      "version": "Latest",
      "category": "suse",
      "download_url": "https://download.opensuse.org/tumbleweed/iso/openSUSE-Tumbleweed-DVD-x86_64-Current.iso",
      "sha256": "PLACEHOLDER_HASH_UPDATE_WITH_REAL_HASH",
      "size_bytes": 4700000000,
      "size_human": "4.4 GB",
      "description": "Rolling release with YaST",
      "verified": true
    },
    {
      "id": "elementary-7.1",
      "name": "elementary OS 7.1",
      "version": "7.1",
      "category": "ubuntu",
      "download_url": "https://ams3.dl.elementary.io/download/MTczNzIyMTc1OQ==/elementaryos-7.1-stable.20230926rc.iso",
      "sha256": "PLACEHOLDER_HASH_UPDATE_WITH_REAL_HASH",
      "size_bytes": 3000000000,
      "size_human": "2.8 GB",
      "description": "Beautiful macOS-inspired desktop",
      "verified": true
    },

    {
      "id": "kali-2025.4",
      "name": "Kali Linux 2025.4",
      "version": "2025.4",
      "category": "debian",
      "download_url": "https://cdimage.kali.org/current/kali-linux-2025.4-installer-amd64.iso",
      "sha256": "PLACEHOLDER_HASH_UPDATE_WITH_REAL_HASH",
      "size_bytes": 4300000000,
      "size_human": "4.0 GB",
      "description": "Penetration testing and security auditing",
      "verified": true
    },
    {
      "id": "endeavouros-2024",
      "name": "EndeavourOS",
      "version": "2024.01",
      "category": "arch",
      "download_url": "https://github.com/endeavouros-team/ISO/releases/download/1-EndeavourOS-ISO-releases-archive/EndeavourOS_Cassini_Nova-03-2023.iso",
      "sha256": "PLACEHOLDER_HASH_UPDATE_WITH_REAL_HASH",
      "size_bytes": 2500000000,
      "size_human": "2.3 GB",
      "description": "Arch-based with easy installer",
      "verified": true
    },



    {
      "id": "garuda-dr460nized",
      "name": "Garuda Linux Dr460nized",
      "version": "Latest",
      "category": "gaming",
      "download_url": "https://iso.builds.garudalinux.org/iso/latest/garuda/dr460nized/latest.iso",
      "sha256": "PLACEHOLDER_HASH_UPDATE_WITH_REAL_HASH",
      "size_bytes": 3500000000,
      "size_human": "3.3 GB",
      "description": "Beautiful gaming-optimized Arch distro",
      "verified": true
    },
    {
      "id": "nobara-43-official",
      "name": "Nobara 43 Official",
      "version": "43",
      "category": "gaming",
      "download_url": "https://nobara-images.nobaraproject.org/Nobara-43-Official-2025-12-27.iso",
      "sha256": "PLACEHOLDER_HASH_UPDATE_WITH_REAL_HASH",
      "size_bytes": 3200000000,
      "size_human": "3.0 GB",
      "description": "Fedora-based gaming distro with performance tweaks",
      "verified": true
    },
    {
      "id": "chimeraos-2025-02-13",
      "name": "ChimeraOS",
      "version": "2025.02.13",
      "category": "gaming",
      "download_url": "https://github.com/ChimeraOS/install-media/releases/download/2025-02-13_7e927cf/chimeraos-2025.02.13-x86_64.iso",
      "sha256": "PLACEHOLDER_HASH_UPDATE_WITH_REAL_HASH",
      "size_bytes": 1800000000,
      "size_human": "1.7 GB",
      "description": "SteamOS-like gaming OS for PC",
      "verified": true
    },
    {
      "id": "cachyos-desktop-251129",
      "name": "CachyOS Desktop",
      "version": "2024.11.29",
      "category": "gaming",
      "download_url": "https://cdn77.cachyos.org/ISO/desktop/251129/cachyos-desktop-linux-251129.iso",
      "sha256": "PLACEHOLDER_HASH_UPDATE_WITH_REAL_HASH",
      "size_bytes": 2400000000,
      "size_human": "2.2 GB",
      "description": "Performance-optimized Arch Linux with custom kernel",
      "verified": true
    },
    {
      "id": "mx-linux-23",
      "name": "MX Linux 23",
      "version": "23",
      "category": "debian",
      "download_url": "https://sourceforge.net/projects/mx-linux/files/Final/Xfce/MX-23_x64.iso/download",
      "sha256": "PLACEHOLDER_HASH_UPDATE_WITH_REAL_HASH",
      "size_bytes": 2200000000,
      "size_human": "2.1 GB",
      "description": "Stable midweight Debian-based distro",
      "verified": true
    },
    {
      "id": "nixos-24.11",
      "name": "NixOS 24.11 Plasma",
      "version": "24.11",
      "category": "other",
      "download_url": "https://releases.nixos.org/nixos/24.11/nixos-24.11.20250118.9ddcbaa/nixos-plasma-24.11.20250118.9ddcbaa-x86_64-linux.iso",
      "sha256": "PLACEHOLDER_HASH_UPDATE_WITH_REAL_HASH",
      "size_bytes": 3100000000,
      "size_human": "2.9 GB",
      "description": "Declarative Linux with reproducible builds",
      "verified": true
    },
    {
      "id": "alpine-3.21",
      "name": "Alpine Linux 3.21",
      "version": "3.21.0",
      "category": "other",
      "download_url": "https://dl-cdn.alpinelinux.org/alpine/v3.21/releases/x86_64/alpine-standard-3.21.0-x86_64.iso",
      "sha256": "PLACEHOLDER_HASH_UPDATE_WITH_REAL_HASH",
      "size_bytes": 200000000,
      "size_human": "190 MB",
      "description": "Minimal security-focused Linux for containers",
      "verified": true
    },
    {
      "id": "artix-plasma",
      "name": "Artix Linux KDE Plasma",
      "version": "Rolling",
      "category": "arch",
      "download_url": "https://iso.artixlinux.org/iso/artix-plasma-runit-20231127-x86_64.iso",
      "sha256": "PLACEHOLDER_HASH_UPDATE_WITH_REAL_HASH",
      "size_bytes": 2800000000,
      "size_human": "2.6 GB",
      "description": "Arch without systemd - uses runit/OpenRC",
      "verified": true
    },
    {
      "id": "tails-6.10",
      "name": "Tails 6.10",
      "version": "6.10",
      "category": "other",
      "download_url": "https://mirrors.wikimedia.org/tails/stable/tails-amd64-7.4/tails-amd64-7.4.img",
      "sha256": "PLACEHOLDER_HASH_UPDATE_WITH_REAL_HASH",
      "size_bytes": 1400000000,
      "size_human": "1.3 GB",
      "description": "Privacy-focused Debian for anonymous browsing",
      "verified": true
    },
    {
      "id": "qubes-os-4.2",
      "name": "Qubes OS 4.2",
      "version": "4.2.3",
      "category": "other",
      "download_url": "https://mirrors.edge.kernel.org/qubes/iso/Qubes-R4.2.3-x86_64.iso",
      "sha256": "PLACEHOLDER_HASH_UPDATE_WITH_REAL_HASH",
      "size_bytes": 5900000000,
      "size_human": "5.5 GB",
      "description": "Security-focused OS with VM compartmentalization",
      "verified": true
    },
    {
      "id": "endeavouros-2026",
      "name": "EndeavourOS",
      "version": "2026.01",
      "category": "arch",
      "download_url": "https://github.com/endeavouros-team/ISO/releases/download/2024.09.22/EndeavourOS_Endeavour-2024.09.22.iso",
      "sha256": "PLACEHOLDER_HASH_UPDATE_WITH_REAL_HASH",
      "size_bytes": 2400000000,
      "size_human": "2.2 GB",
      "description": "User-friendly Arch with GUI installer",
      "verified": true
    },
    {
      "id": "garuda-linux-kde",
      "name": "Garuda Linux KDE",
      "version": "2026.01",
      "category": "gaming",
      "download_url": "https://iso.builds.garudalinux.org/iso/latest/garuda/kde-lite/latest.iso",
      "sha256": "PLACEHOLDER_HASH_UPDATE_WITH_REAL_HASH",
      "size_bytes": 3100000000,
      "size_human": "2.9 GB",
      "description": "Gaming-focused Arch with beautiful KDE",
      "verified": true
    },
    {
      "id": "mx-linux-23",
      "name": "MX Linux 23",
      "version": "23.4 KDE",
      "category": "debian",
      "download_url": "https://sourceforge.net/projects/mx-linux/files/Final/KDE/MX-23.4_KDE_x64.iso/download",
      "sha256": "PLACEHOLDER_HASH_UPDATE_WITH_REAL_HASH",
      "size_bytes": 2900000000,
      "size_human": "2.7 GB",
      "description": "Lightweight Debian with MX Tools suite",
      "verified": true
    },
    {
      "id": "antiX-23",
      "name": "antiX 23",
      "version": "23.1",
      "category": "debian",
      "download_url": "https://sourceforge.net/projects/antix-linux/files/Final/antiX-23.1/antiX-23.1_x64-full.iso/download",
      "sha256": "PLACEHOLDER_HASH_UPDATE_WITH_REAL_HASH",
      "size_bytes": 1300000000,
      "size_human": "1.2 GB",
      "description": "Ultra-lightweight for old hardware",
      "verified": true
    },
    {
      "id": "blendos-4",
      "name": "blendOS",
      "version": "4.0",
      "category": "arch",
      "download_url": "https://github.com/blend-os/blendOS/releases/download/v4.0.0/blendOS-v4.0.0.iso",
      "sha256": "PLACEHOLDER_HASH_UPDATE_WITH_REAL_HASH",
      "size_bytes": 2000000000,
      "size_human": "1.9 GB",
      "description": "Immutable Arch with container integration",
      "verified": true
    },
    {
      "id": "bodhi-linux-7",
      "name": "Bodhi Linux 7",
      "version": "7.0.0",
      "category": "ubuntu",
      "download_url": "https://sourceforge.net/projects/bodhilinux/files/7.0.0/bodhi-7.0.0-64.iso/download",
      "sha256": "PLACEHOLDER_HASH_UPDATE_WITH_REAL_HASH",
      "size_bytes": 1200000000,
      "size_human": "1.1 GB",
      "description": "Lightweight Ubuntu with Moksha desktop",
      "verified": true
    },
    {
      "id": "rockylinux-9",
      "name": "Rocky Linux 9.7",
      "version": "9.7",
      "category": "fedora",
      "download_url": "https://download.rockylinux.org/pub/rocky/9/isos/x86_64/Rocky-9.7-x86_64-dvd.iso",
      "sha256": "PLACEHOLDER_HASH_UPDATE_WITH_REAL_HASH",
      "size_bytes": 12741000000,
      "size_human": "11.9 GB",
      "description": "RHEL-compatible enterprise Linux",
      "verified": true
    },
    {
      "id": "almalinux-9",
      "name": "AlmaLinux 9.7",
      "version": "9.7",
      "category": "fedora",
      "download_url": "https://repo.almalinux.org/almalinux/9/isos/x86_64/AlmaLinux-9.7-x86_64-dvd.iso",
      "sha256": "PLACEHOLDER_HASH_UPDATE_WITH_REAL_HASH",
      "size_bytes": 12720000000,
      "size_human": "11.9 GB",
      "description": "Community-driven RHEL fork",
      "verified": true
    },

    {
      "id": "parrot-security-6",
      "name": "Parrot Security OS 6",
      "version": "6.0",
      "category": "debian",
      "download_url": "https://deb.parrot.sh/parrot/iso/6.0/Parrot-security-6.0_amd64.iso",
      "sha256": "PLACEHOLDER_HASH_UPDATE_WITH_REAL_HASH",
      "size_bytes": 4200000000,
      "size_human": "3.9 GB",
      "description": "Security and pentesting distro",
      "verified": true
    },
    {
      "id": "blackarch-2024",
      "name": "BlackArch Linux",
      "version": "2024.01",
      "category": "arch",
      "download_url": "https://mirrors.ocf.berkeley.edu/blackarch/iso/blackarch-linux-live-2024.01.01-x86_64.iso",
      "sha256": "PLACEHOLDER_HASH_UPDATE_WITH_REAL_HASH",
      "size_bytes": 16000000000,
      "size_human": "15 GB",
      "description": "Penetration testing Arch with 2800+ tools",
      "verified": true
    },
    {
      "id": "athena-os-2024",
      "name": "Athena OS",
      "version": "2024.01",
      "category": "arch",
      "download_url": "https://github.com/Athena-OS/athena/releases/download/v24.01/athena-2024.01-x86_64.iso",
      "sha256": "PLACEHOLDER_HASH_UPDATE_WITH_REAL_HASH",
      "size_bytes": 3800000000,
      "size_human": "3.5 GB",
      "description": "Modern pentesting Arch distro",
      "verified": true
    },

    {
      "id": "raspios-64bit",
      "name": "Raspberry Pi OS (64-bit)",
      "version": "2024-07-04",
      "category": "raspberry",
      "download_url": "https://downloads.raspberrypi.com/raspios_arm64/images/raspios_arm64-2024-07-04/2024-07-04-raspios-bookworm-arm64.img.xz",
      "sha256": "PLACEHOLDER_HASH_UPDATE_WITH_REAL_HASH",
      "size_bytes": 1100000000,
      "size_human": "1.0 GB",
      "description": "Official Pi desktop • ARM64 • RPi optimized",
      "verified": true
    },
    {
      "id": "raspios-lite-64bit",
      "name": "Raspberry Pi OS Lite (64-bit)",
      "version": "2024-07-04",
      "category": "raspberry",
      "download_url": "https://downloads.raspberrypi.com/raspios_lite_arm64/images/raspios_lite_arm64-2024-07-04/2024-07-04-raspios-bookworm-arm64-lite.img.xz",
      "sha256": "PLACEHOLDER_HASH_UPDATE_WITH_REAL_HASH",
      "size_bytes": 500000000,
      "size_human": "477 MB",
      "description": "Headless server • ARM64 • SSH • no GUI",
      "verified": true
    },

    {
      "id": "fedora-server-40",
      "name": "Fedora Server 40",
      "version": "40",
      "category": "fedora",
      "download_url": "https://download.fedoraproject.org/pub/fedora/linux/releases/40/Server/x86_64/iso/Fedora-Server-dvd-x86_64-40-1.14.iso",
      "sha256": "PLACEHOLDER_HASH_UPDATE_WITH_REAL_HASH",
      "size_bytes": 2300000000,
      "size_human": "2.1 GB",
      "description": "Fedora for servers",
      "verified": true
    },
    {
      "id": "fedora-silverblue-41",
      "name": "Fedora Silverblue 41",
      "version": "41",
      "category": "fedora",
      "download_url": "https://download.fedoraproject.org/pub/fedora/linux/releases/41/Silverblue/x86_64/iso/Fedora-Silverblue-ostree-x86_64-41-1.4.iso",
      "sha256": "PLACEHOLDER_HASH_UPDATE_WITH_REAL_HASH",
      "size_bytes": 2600000000,
      "size_human": "2.4 GB",
      "description": "Immutable Fedora with Flatpaks",
      "verified": true
    },
    {
      "id": "fedora-kinoite-41",
      "name": "Fedora Kinoite 41",
      "version": "41",
      "category": "fedora",
      "download_url": "https://download.fedoraproject.org/pub/fedora/linux/releases/41/Kinoite/x86_64/iso/Fedora-Kinoite-ostree-x86_64-41-1.4.iso",
      "sha256": "PLACEHOLDER_HASH_UPDATE_WITH_REAL_HASH",
      "size_bytes": 2600000000,
      "size_human": "2.4 GB",
      "description": "Immutable Fedora with KDE Plasma",
      "verified": true
    },
    {
      "id": "popos-2404",
      "name": "Pop!_OS 24.04 LTS",
      "version": "24.04",
      "category": "ubuntu",
      "download_url": "https://iso.pop-os.org/24.04/amd64/intel/52/pop-os_24.04_amd64_intel_52.iso",
      "sha256": "PLACEHOLDER_HASH_UPDATE_WITH_REAL_HASH",
      "size_bytes": 3200000000,
      "size_human": "3.0 GB",
      "description": "Gaming & dev Ubuntu • x86_64 • COSMIC DE",
      "verified": true
    },
    {
      "id": "popos-nvidia-2404",
      "name": "Pop!_OS 24.04 (NVIDIA)",
      "version": "24.04",
      "category": "ubuntu",
      "download_url": "https://iso.pop-os.org/24.04/amd64/nvidia/52/pop-os_24.04_amd64_nvidia_52.iso",
      "sha256": "PLACEHOLDER_HASH_UPDATE_WITH_REAL_HASH",
      "size_bytes": 3400000000,
      "size_human": "3.2 GB",
      "description": "Pop OS with NVIDIA drivers • x86_64",
      "verified": true
    },
    {
      "id": "elementary-7.1",
      "name": "elementary OS 7.1",
      "version": "7.1",
      "category": "ubuntu",
      "download_url": "https://ams3.dl.elementary.io/download/latest/elementaryos-7.1-stable.20230926rc.iso",
      "sha256": "PLACEHOLDER_HASH_UPDATE_WITH_REAL_HASH",
      "size_bytes": 3000000000,
      "size_human": "2.8 GB",
      "description": "macOS-like Ubuntu • x86_64 • Pantheon DE",
      "verified": true
    },
    {
      "id": "zorin-os-17-core",
      "name": "Zorin OS 17 Core",
      "version": "17.1",
      "category": "ubuntu",
      "download_url": "https://sourceforge.net/projects/zorinos/files/17/Zorin-OS-17.1-Core-64-bit.iso/download",
      "sha256": "PLACEHOLDER_HASH_UPDATE_WITH_REAL_HASH",
      "size_bytes": 3100000000,
      "size_human": "2.9 GB",
      "description": "Windows-like Ubuntu • x86_64 • beginners",
      "verified": true
    },
    {
      "id": "linux-lite-7.0",
      "name": "Linux Lite 7.0",
      "version": "7.0",
      "category": "ubuntu",
      "download_url": "https://sourceforge.net/projects/linux-lite/files/7.0/linux-lite-7.0-64bit.iso/download",
      "sha256": "PLACEHOLDER_HASH_UPDATE_WITH_REAL_HASH",
      "size_bytes": 2600000000,
      "size_human": "2.4 GB",
      "description": "Lightweight Ubuntu • x86_64 • old hardware",
      "verified": true
    },
    {
      "id": "steamos-3.6",
      "name": "SteamOS 3.6",
      "version": "3.6",
      "category": "gaming",
      "download_url": "https://steamdeck-images.steamos.cloud/recovery/steamdeck-recovery-4.img.bz2",
      "sha256": "PLACEHOLDER_HASH_UPDATE_WITH_REAL_HASH",
      "size_bytes": 4500000000,
      "size_human": "4.2 GB",
      "description": "Valve's gaming OS • x86_64 • Steam Deck",
      "verified": true
    },
    {
      "id": "alpinelinux-3.19",
      "name": "Alpine Linux 3.19",
      "version": "3.19.1",
      "category": "other",
      "download_url": "https://dl-cdn.alpinelinux.org/alpine/v3.19/releases/x86_64/alpine-standard-3.19.1-x86_64.iso",
      "sha256": "PLACEHOLDER_HASH_UPDATE_WITH_REAL_HASH",
      "size_bytes": 200000000,
      "size_human": "191 MB",
      "description": "Minimal musl Linux • x86_64/ARM • containers",
      "verified": true
    },
    {
      "id": "void-linux-2024",
      "name": "Void Linux",
      "version": "2024.01",
      "category": "other",
      "download_url": "https://repo-default.voidlinux.org/live/current/void-live-x86_64-20250202-base.iso",
      "sha256": "PLACEHOLDER_HASH_UPDATE_WITH_REAL_HASH",
      "size_bytes": 900000000,
      "size_human": "858 MB",
      "description": "Rolling runit • x86_64/ARM • no systemd",
      "verified": true
    },

    {
      "id": "tails-6.0",
      "name": "Tails 6.0",
      "version": "6.0",
      "category": "debian",
      "download_url": "https://tails.net/torrents/files/tails-amd64-6.0.iso",
      "sha256": "PLACEHOLDER_HASH_UPDATE_WITH_REAL_HASH",
      "size_bytes": 1400000000,
      "size_human": "1.3 GB",
      "description": "Privacy & anonymity • x86_64 • Tor • amnesia",
      "verified": true
    },
    {
      "id": "qubes-4.2",
      "name": "Qubes OS 4.2",
      "version": "4.2.0",
      "category": "other",
      "download_url": "https://mirrors.edge.kernel.org/qubes/iso/Qubes-R4.2.0-x86_64.iso",
      "sha256": "PLACEHOLDER_HASH_UPDATE_WITH_REAL_HASH",
      "size_bytes": 6500000000,
      "size_human": "6.1 GB",
      "description": "Security by isolation • x86_64 • Xen VMs",
      "verified": true
    },
    {
      "id": "openwrt-23.05",
      "name": "OpenWrt 23.05",
      "version": "23.05.3",
      "category": "raspberry",
      "download_url": "https://downloads.openwrt.org/releases/23.05.3/targets/x86/64/openwrt-23.05.3-x86-64-generic-ext4-combined.img.gz",
      "sha256": "PLACEHOLDER_HASH_UPDATE_WITH_REAL_HASH",
      "size_bytes": 150000000,
      "size_human": "143 MB",
      "description": "Router/firewall OS • x86/ARM • networking",
      "verified": true
    },
    {
      "id": "coreos-stable",
      "name": "CoreOS Stable",
      "version": "39.20240128",
      "category": "fedora",
      "download_url": "https://builds.coreos.fedoraproject.org/prod/streams/stable/builds/39.20240128.3.0/x86_64/fedora-coreos-39.20240128.3.0-live.x86_64.iso",
      "sha256": "PLACEHOLDER_HASH_UPDATE_WITH_REAL_HASH",
      "size_bytes": 1000000000,
      "size_human": "954 MB",
      "description": "Container OS • x86_64/ARM • immutable • k8s",
      "verified": true
    },
    {
      "id": "photon-5.0",
      "name": "Photon OS 5.0",
      "version": "5.0",
      "category": "other",
      "download_url": "https://packages.vmware.com/photon/5.0/GA/iso/photon-5.0-dde71ec57.x86_64.iso",
      "sha256": "PLACEHOLDER_HASH_UPDATE_WITH_REAL_HASH",
      "size_bytes": 500000000,
      "size_human": "477 MB",
      "description": "VMware minimal • x86_64/ARM • containers",
      "verified": true
    },
    {
      "id": "alma-micro-9",
      "name": "AlmaLinux 9 Micro",
      "version": "9.3",
      "category": "fedora",
      "download_url": "https://repo.almalinux.org/almalinux/9.3/isos/x86_64/AlmaLinux-9.3-x86_64-minimal.iso",
      "sha256": "PLACEHOLDER_HASH_UPDATE_WITH_REAL_HASH",
      "size_bytes": 2000000000,
      "size_human": "1.9 GB",
      "description": "RHEL clone minimal • x86_64/ARM • servers",
      "verified": true
    },
    {
      "id": "debian-live-12.5",
      "name": "Debian 12.5 Live",
      "version": "12.5",
      "category": "debian",
      "download_url": "https://cdimage.debian.org/debian-cd/current-live/amd64/iso-hybrid/debian-live-12.5.0-amd64-gnome.iso",
      "sha256": "PLACEHOLDER_HASH_UPDATE_WITH_REAL_HASH",
      "size_bytes": 3200000000,
      "size_human": "3.0 GB",
      "description": "Universal Linux • x86_64/ARM • stable",
      "verified": true
    },
    {
      "id": "ubuntu-server-24.04",
      "name": "Ubuntu Server 24.04 LTS",
      "version": "24.04",
      "category": "ubuntu",
      "download_url": "https://releases.ubuntu.com/24.04/ubuntu-24.04.1-live-server-amd64.iso",
      "sha256": "PLACEHOLDER_HASH_UPDATE_WITH_REAL_HASH",
      "size_bytes": 2700000000,
      "size_human": "2.5 GB",
      "description": "Server LTS • x86_64/ARM • cloud-ready",
      "verified": true
    },
    {
      "id": "arch-202401",
      "name": "Arch Linux",
      "version": "2024.01.01",
      "category": "arch",
      "download_url": "https://geo.mirror.pkgbuild.com/iso/2024.01.01/archlinux-2024.01.01-x86_64.iso",
      "sha256": "PLACEHOLDER_HASH_UPDATE_WITH_REAL_HASH",
      "size_bytes": 900000000,
      "size_human": "858 MB",
      "description": "Minimalist rolling • x86_64 • bleeding edge",
      "verified": true
    },
    {
      "id": "ubuntu-studio-24.04",
      "name": "Ubuntu Studio 24.04",
      "version": "24.04",
      "category": "ubuntu",
      "download_url": "https://cdimage.ubuntu.com/ubuntustudio/releases/24.04/release/ubuntustudio-24.04-dvd-amd64.iso",
      "sha256": "PLACEHOLDER_HASH_UPDATE_WITH_REAL_HASH",
      "size_bytes": 4500000000,
      "size_human": "4.2 GB",
      "description": "Audio/video production • x86_64 • pro content",
      "verified": true
    },


    {
      "id": "debian-12-netinst",
      "name": "Debian 13 Netinst",
      "version": "13.3",
      "category": "debian",
      "download_url": "https://cdimage.debian.org/debian-cd/current/amd64/iso-cd/debian-13.3.0-amd64-netinst.iso",
      "sha256": "PLACEHOLDER_HASH_UPDATE_WITH_REAL_HASH",
      "size_bytes": 700000000,
      "size_human": "668 MB",
      "description": "Minimal installer • x86_64/ARM • stable",
      "verified": true
    },
    {
      "id": "proxmox-ve-8",
      "name": "Proxmox VE 9.1",
      "version": "9.1",
      "category": "debian",
      "download_url": "https://enterprise.proxmox.com/iso/proxmox-ve_9.1-1.iso",
      "sha256": "PLACEHOLDER_HASH_UPDATE_WITH_REAL_HASH",
      "size_bytes": 1747000000,
      "size_human": "1.6 GB",
      "description": "Virtualization platform • x86_64 • pro/homelab",
      "verified": true
    },
    {
      "id": "truenas-scale-24",
      "name": "TrueNAS SCALE 24.04.2.3",
      "version": "24.04.2.3",
      "category": "debian",
      "download_url": "https://download.truenas.com/TrueNAS-SCALE-Dragonfish/24.04.2.3/TrueNAS-SCALE-24.04.2.3.iso",
      "sha256": "PLACEHOLDER_HASH_UPDATE_WITH_REAL_HASH",
      "size_bytes": 1554000000,
      "size_human": "1.5 GB",
      "description": "NAS/storage • x86_64 • ZFS • containers",
      "verified": true
    },
    {
      "id": "opnsense-24.1",
      "name": "OPNsense 25.1",
      "version": "25.1",
      "category": "other",
      "download_url": "https://opnsense.c0urier.net/releases/25.1/OPNsense-25.1-dvd-amd64.iso.bz2",
      "sha256": "PLACEHOLDER_HASH_UPDATE_WITH_REAL_HASH",
      "size_bytes": 497200000,
      "size_human": "474 MB",
      "description": "Firewall/router • x86_64 • FreeBSD • pro",
      "verified": true
    },
    {
      "id": "pfsense-2.7",
      "name": "pfSense CE 2.7.2",
      "version": "2.7.2",
      "category": "other",
      "download_url": "https://atxfiles.netgate.com/mirror/downloads/pfSense-CE-2.7.2-RELEASE-amd64.iso.gz",
      "sha256": "PLACEHOLDER_HASH_UPDATE_WITH_REAL_HASH",
      "size_bytes": 547600000,
      "size_human": "522 MB",
      "description": "Firewall/VPN • x86_64 • enterprise ready",
      "verified": true
    },
    {
      "id": "centos-stream-9",
      "name": "CentOS Stream 9",
      "version": "9",
      "category": "fedora",
      "download_url": "https://mirrors.centos.org/mirrorlist?path=/9-stream/BaseOS/x86_64/iso/CentOS-Stream-9-latest-x86_64-dvd1.iso",
      "sha256": "PLACEHOLDER_HASH_UPDATE_WITH_REAL_HASH",
      "size_bytes": 9500000000,
      "size_human": "8.8 GB",
      "description": "RHEL upstream • x86_64/ARM • rolling preview",
      "verified": true
    }

  ]
}